src/pyAR488_Minu_UI3IRR/__init__.py
src/pyAR488_Minu_UI3IRR/pyAR488.py
pyar488_minu_iu3irr-0.11.dist-info/METADATA
pyar488_minu_iu3irr-0.11.dist-info/WHEEL
pyar488_minu_iu3irr-0.11.dist-info/licenses/LICENSE
pyar488_minu_iu3irr-0.11.dist-info/RECORD
