Metadata-Version: 2.1
Name: pyAr488_Minu_IU3IRR
Version: 0.11
Summary: module to interface AR488 interfaces
Project-URL: Homepage, https://github.com/Minu-IU3IRR/AR488/blob/master/pyAR488.py
Project-URL: Bug Tracker, https://github.com/Minu-IU3IRR/AR488/issues
Author: Manuel Minutello
License-File: LICENSE
Classifier: License :: OSI Approved :: MIT License
Classifier: Operating System :: OS Independent
Classifier: Programming Language :: Python :: 3
Requires-Python: >=3.7
